{
  "slide": {
    "indexh": 1,
    "indexv": 0
  },
  "Special Lines": [
    {
      "PAUSE": true
    },
    {
      "TIMER": "ON"
    },
    {
      "TIMER": "OFF"
    },
    {
      "DEBUG": "CALL myTimer - >>>>>>>>>>>>>>>>>>>>>>>>>>>>>>>>>>>>>>>>>>>>>>>>>>>>>>>>>>>>>>>>>>>>>>>>>>>"
    }
  ],
  "sampleSteps": {
    "lineNumber": "#",
    "stack": "+|MESSAGE",
    "webAPI": "+|MESSAGE",
    "taskQueue": "+|MESSAGE",
    "microtaskQueue": "+|MESSAGE",
    "console": "+|MESSAGE"
  },
  "config": {
    "delay": 500,
    "autoNext": true
  },
  "demos": [
    {
      "name": "Sample: Basic calls (Understand UI)",
      "code": "SampleBasicCalls"
    },
    {
      "name": "Sample: Multiple Timers",
      "code": "SampleMultipleTimers"
    },
    {
      "name": "Sample: Promises",
      "code": "SamplePromises"
    },
    {
      "name": "Other: Wait Zero milliseconds",
      "code": "OtherSetTimeoutZero"
    },
    {
      "name": "Other: Chaining Methods",
      "code": "OtherMethodsChained"
    },
    {
      "name": "Other: Simple Timer",
      "code": "OtherSetTimeout"
    },
    {
      "name": "TEST: Fill the boxes",
      "code": "TestFillBoxes"
    },
    {
      "name": "TEST: Long (scrolls)",
      "code": "TestLongScrolls"
    }
  ]
}
